ml235/__init__.py
ml235/main.py
ml235-0.0.1.dist-info/METADATA
ml235-0.0.1.dist-info/WHEEL
ml235-0.0.1.dist-info/licenses/LICENSE
ml235-0.0.1.dist-info/RECORD
