Metadata-Version: 2.3
Name: ml235
Version: 0.0.1
Summary: ?
Author-email: matmak <matmak@list.ru>
License-File: LICENSE
Classifier: License :: OSI Approved :: MIT License
Classifier: Operating System :: OS Independent
Classifier: Programming Language :: Python :: 3
Requires-Python: >=3.10.0
